{"name":"Ensure encrypted storage is used for VMs that might host a database","slug":"aws-ec2-2","body":"If you have to or choose to host the database on a virtual machine, encrypting the volumes is highly recommended.\n\nThe system determines this based on the VM name.","description":"","severity":2,"remediationDescription":"Consult the following [AWS article](https://aws.amazon.com/blogs/security/architecting-for-database-encryption-on-aws/) describing various alternatives for database encryption.","rules":[{"cloudProviders":["aws"],"comparator":"eq","expectedResult":"[]","subjects":["VM"],"query":"aws-ec2-2-encrypted-storage-is-used-for-vms-that-might-host-a-database","returnPath":""}]}