{"name":"Ensure AWS Inspector is configured for EC2 Instances","slug":"aws-scan-1","body":"AWS Inspector is a security assessment service, used to assess applications for vulnerabilities or deviations from best practices. It is recommended to run AWS Inspector scans regularly.","description":"","severity":1,"remediationDescription":"Follow the [AWS Article](https://aws.amazon.com/premiumsupport/knowledge-center/set-up-amazon-inspector/) describing how to set up AWS Inspector for your instances. Additionally, we also recommend to set up periodic scans through Recurring Assessment Runs.","rules":[{"cloudProviders":["aws"],"comparator":"eq","expectedResult":"[]","subjects":["VM"],"query":"aws-scan-1-aws-inspector-is-configured-for-ec2-instances","returnPath":""}]}